README.txt
setup.cfg
setup.py
Products/__init__.py
Products.tagNavigator.egg-info/PKG-INFO
Products.tagNavigator.egg-info/SOURCES.txt
Products.tagNavigator.egg-info/dependency_links.txt
Products.tagNavigator.egg-info/entry_points.txt
Products.tagNavigator.egg-info/namespace_packages.txt
Products.tagNavigator.egg-info/not-zip-safe
Products.tagNavigator.egg-info/paster_plugins.txt
Products.tagNavigator.egg-info/requires.txt
Products.tagNavigator.egg-info/top_level.txt
Products/tagNavigator/__init__.py
Products/tagNavigator/categoryutils.py
Products/tagNavigator/configure.zcml
Products/tagNavigator/tests.py
Products/tagNavigator/browser/__init__.py
Products/tagNavigator/browser/configure.zcml
Products/tagNavigator/browser/interfaces.py
Products/tagNavigator/browser/tagnavigator_view.pt
Products/tagNavigator/browser/tagnavigator_view.py
Products/tagNavigator/browser/javascripts/tagCollapse.js
Products/tagNavigator/browser/stylesheets/tagNavigator.css
Products/tagNavigator/portlets/__init__.py
Products/tagNavigator/portlets/configure.zcml
Products/tagNavigator/portlets/tagnavigator.pt
Products/tagNavigator/portlets/tagnavigator.py
Products/tagNavigator/profiles/default/cssregistry.xml
Products/tagNavigator/profiles/default/jsregistry.xml
Products/tagNavigator/profiles/default/metadata.xml
Products/tagNavigator/profiles/default/portlets.xml
Products/tagNavigator/profiles/default/types/Folder.xml
Products/tagNavigator/profiles/default/types/Topic.xml
docs/HISTORY.txt
docs/INSTALL.txt
docs/LICENSE.GPL
docs/LICENSE.txt