Metadata-Version: 1.0
Name: Products.tagNavigator
Version: 0.7
Summary: Portlet for tag navigation inside a container
Home-page: http://svn.plone.org/svn/collective/
Author: David Jonas
Author-email: david@itsnotthatkind.org
License: GPL
Keywords: tag category navigation portlet
Platform: UNKNOWN
Classifier: Framework :: Plone
Classifier: Programming Language :: Python
